Metadata-Version: 1.0
Name: aiauthenticator
Version: 0.3
Summary: Ai Authenticator for JupyterHub
Home-page: https://github.com/jiangjialong/aiauthenticator
Author: jiangjialong
Author-email: 422352011@qq.com
License: 3 Clause BSD
Platform: UNKNOWN
